mercury.cpython-38-aarch64-linux-gnu.so
mercury_python_test-0.1.2.dist-info/COPYING
mercury_python_test-0.1.2.dist-info/LICENSE
mercury_python_test-0.1.2.dist-info/METADATA
mercury_python_test-0.1.2.dist-info/top_level.txt
mercury_python_test-0.1.2.dist-info/RECORD
mercury_python_test-0.1.2.dist-info/WHEEL
mercury_python_test.libs/libcrypto-13880bfc.so.1.0.2k
