Metadata-Version: 2.1
Name: mercury-python-test
Version: 0.1.2
Summary: Python interface into mercury's network protocol fingerprinting and analysis functionality
Home-page: https://github.com/cisco/mercury-python/
Author: Blake Anderson
Author-email: blake.anderson@cisco.com
Keywords: tls fingerprinting network traffic analysis
Classifier: Development Status :: 3 - Alpha
Classifier: Programming Language :: Python :: 3 :: Only
Classifier: Topic :: System :: Networking :: Monitoring
Classifier: Topic :: Security
Requires-Python: >=3.6.0
License-File: LICENSE
License-File: COPYING
